universal_history/__init__.py
universal_history/config.py
universal_history/models/__init__.py
universal_history/models/domain_catalog.py
universal_history/models/event_record.py
universal_history/models/state_document.py
universal_history/models/trajectory_synthesis.py
universal_history/models/universal_history.py
universal_history/services/__init__.py
universal_history/services/event_service.py
universal_history/services/history_service.py
universal_history/services/state_service.py
universal_history/services/synthesis_service.py
universal_history/storage/__init__.py
universal_history/storage/memory_repository.py
universal_history/storage/mongodb_repository.py
universal_history/storage/repository.py
universal_history/utils/__init__.py
universal_history/utils/hash_utils.py
universal_history/utils/time_utils.py
universal_history/utils/validation.py
universal_history-0.1.2.dist-info/METADATA
universal_history-0.1.2.dist-info/WHEEL
universal_history-0.1.2.dist-info/top_level.txt
universal_history-0.1.2.dist-info/RECORD
