Metadata-Version: 2.4
Name: universal-history
Version: 0.1.2
Summary: A library for creating, maintaining, and utilizing Universal Histories across multiple domains
Author-email: Original Author <author@example.com>
License-Expression: MIT
Project-URL: Homepage, https://github.com/yourusername/universal-history
Project-URL: Issues, https://github.com/yourusername/universal-history/issues
Project-URL: Documentation, https://universal-history.readthedocs.io/
Classifier: Development Status :: 3 - Alpha
Classifier: Intended Audience :: Developers
Classifier: Programming Language :: Python :: 3
Classifier: Programming Language :: Python :: 3.8
Classifier: Programming Language :: Python :: 3.9
Classifier: Programming Language :: Python :: 3.10
Classifier: Programming Language :: Python :: 3.11
Classifier: Topic :: Software Development :: Libraries
Requires-Python: >=3.8
Requires-Dist: pymongo>=4.0.0
Requires-Dist: pydantic>=2.0.0
Requires-Dist: python-dateutil>=2.8.0
Provides-Extra: dev
Requires-Dist: pytest>=7.0.0; extra == "dev"
Requires-Dist: pytest-cov>=4.0.0; extra == "dev"
Requires-Dist: black>=23.0.0; extra == "dev"
Requires-Dist: isort>=5.12.0; extra == "dev"
Requires-Dist: mypy>=1.0.0; extra == "dev"
Requires-Dist: flake8>=6.0.0; extra == "dev"
Provides-Extra: mongodb
Requires-Dist: pymongo>=4.0.0; extra == "mongodb"
Provides-Extra: llm
Requires-Dist: langchain>=0.0.267; extra == "llm"
Requires-Dist: numpy>=1.20.0; extra == "llm"
